botoful/__init__.py
botoful/filters.py
botoful/query.py
botoful/reserved.py
botoful/serializers.py
botoful/table.py
botoful-0.4.1.dist-info/LICENSE
botoful-0.4.1.dist-info/METADATA
botoful-0.4.1.dist-info/WHEEL
botoful-0.4.1.dist-info/RECORD
