Metadata-Version: 2.1
Name: botoful
Version: 0.4.1
Summary: A beautiful boto wrapper
Home-page: https://www.botoful.com
License: MIT
Author: Imtiaz Mangerah
Author-email: Imtiaz_Mangerah@a2d24.com
Requires-Python: >=3.8,<4.0
Classifier: License :: OSI Approved :: MIT License
Classifier: Programming Language :: Python :: 3
Classifier: Programming Language :: Python :: 3.8
Classifier: Programming Language :: Python :: 3.9
Classifier: Programming Language :: Python :: 3.10
Classifier: Programming Language :: Python :: 3.11
Provides-Extra: boto
Requires-Dist: boto3 (>=1.17.23,<2.0.0) ; extra == "boto"
Project-URL: Documentation, https://www.botoful.com
Project-URL: Repository, https://github.com/a2d24/botoful
